parsinghook/__init__.py
parsinghook/_test.py
parsinghook/auto.py
parsinghook/dumpast.py
parsinghook/hook.py
parsinghook/test.py
parsinghook-0.9.1.dist-info/LICENSE
parsinghook-0.9.1.dist-info/METADATA
parsinghook-0.9.1.dist-info/WHEEL
parsinghook-0.9.1.dist-info/top_level.txt
parsinghook-0.9.1.dist-info/RECORD
