Metadata-Version: 2.1
Name: parsinghook
Version: 0.9.1
Summary: Python parsing hook
Home-page: https://github.com/acaos/python-parsinghook
Author: Doug Swarin
Author-email: dswarin@gmail.com
License: MIT
Project-URL: Bug Tracker, https://github.com/acaos/python-parsinghook/issues
Platform: UNKNOWN
Classifier: Development Status :: 4 - Beta
Classifier: License :: OSI Approved :: MIT License
Classifier: Operating System :: OS Independent
Classifier: Programming Language :: Python :: 3
Classifier: Programming Language :: Python :: 3.8
Classifier: Programming Language :: Python :: 3.9
Classifier: Programming Language :: Python :: 3.10
Requires-Python: >=3.8
License-File: LICENSE
